README.rst
setup.py
zipf_classifier/__init__.py
zipf_classifier/__version__.py
zipf_classifier/split.py
zipf_classifier/zipf_classifier.py
zipf_classifier.egg-info/PKG-INFO
zipf_classifier.egg-info/SOURCES.txt
zipf_classifier.egg-info/dependency_links.txt
zipf_classifier.egg-info/requires.txt
zipf_classifier.egg-info/top_level.txt