Metadata-Version: 1.1
Name: zipf-classifier
Version: 1.5.0
Summary: A package to create a deterministic classifier based on Zipf law
Home-page: https://github.com/LucaCappelletti94/zipf_classifier
Author: Luca Cappelletti
Author-email: cappelletti.luca94@gmail.com
License: MIT
Platform: UNKNOWN
Classifier: Development Status :: 4 - Beta
Classifier: Intended Audience :: Information Technology
Classifier: Topic :: Scientific/Engineering :: Information Analysis
Classifier: License :: OSI Approved :: MIT License
Classifier: Programming Language :: Python :: 3
